Workbook

Sheet Lisez-moi
A1: Chaîne vidéo Espace : 90 vidéos, 3 par jour pendant 30 jours
A3: Calendrier : une ligne par vidéo, dans l'ordre de publication. Script voix-off, 6 prompts d'image, SFX, musique, légende et prompt de production.
A4: Budget : coût estimé par vidéo en 3 formules (Éco / Standard / Premium). Les cellules en bleu sur fond jaune sont modifiables.
A5: Pipeline : les réglages communs (voix, sous-titres, Remotion, publication) et le prompt maître à me donner quand les connecteurs seront branchés.
A6: Banque audio : 12 SFX et 6 musiques à générer une seule fois puis réutiliser (c'est ce qui garde le budget bas).
A8: À modifier : la date de départ (Budget!B4, elle recalcule tout le planning) et la colonne Statut.
A9: Prix relevés sur fal.ai fin septembre 2026, en USD. Ils changent souvent : vérifie avant de lancer en volume.
A10: Les faits scientifiques ont été vérifiés, mais relis chaque script avant publication : sur une chaîne éducative, une erreur coûte cher en crédibilité.

Sheet Calendrier
A1: N° | B1: Jour | C1: Date | D1: Heure | E1: ID | F1: Série | G1: Titre | H1: Script voix-off | I1: Nb caractères | J1: Durée estimée (s) | K1: Scène 1 (hook, animée) | L1: Scène 2 | M1: Scène 3 | N1: Scène 4 | O1: Scène 5 | P1: Scène 6 | Q1: SFX | R1: Musique | S1: Légende + hashtags | T1: Prompt de production | U1: Statut
A2: 1 | B2: 1 | C2: =Budget!$B$4+B2-1 -> 46296 | D2: 08:00 | E2: A01 | F2: Et si… ? | G2: Et si la Lune disparaissait ? | H2: Imagine : ce soir, la Lune disparaît. Pas d'explosion, rien. Elle n'est juste plus là. Premier effet : les marées. Il en resterait, grâce au Soleil, mais elles seraient plus de deux fois plus faibles. Les côtes, les courants, toute la vie qui dépend du rythme des marées serait bouleversée. Les nuits deviendraient beaucoup plus noires. Et sur des millions d'années, l'axe de la Terre, que la Lune stabilise, pourrait se mettre à osciller. Résultat : des climats bien plus chaotiques. Cette petite boule grise nous protège plus qu'on ne le pense. | I2: =LEN(H2) -> 546 | J2: =ROUND(I2/Budget!$B$5,0) -> 36 | K2: Cinematic photorealistic space visualization, NASA/ESA documentary style, dramatic volumetric lighting, deep blacks, rich fine detail, vertical 9:16 composition, main subject in the upper two thirds, no text, no letters, no watermark, no logo. Scene: Full Moon glowing above a calm ocean at night | L2: Cinematic photorealistic space visualization, NASA/ESA documentary style, dramatic volumetric lighting, deep blacks, rich fine detail, vertical 9:16 composition, main subject in the upper two thirds, no text, no letters, no watermark, no logo. Scene: The Moon fading into transparent particles in a starry sky | M2: Cinematic photorealistic space visualization, NASA/ESA documentary style, dramatic volumetric lighting, deep blacks, rich fine detail, vertical 9:16 composition, main subject in the upper two thirds, no text, no letters, no watermark, no logo. Scene: Low tide beach with stranded boats under a dark sky | N2: Cinematic photorealistic space visualization, NASA/ESA documentary style, dramatic volumetric lighting, deep blacks, rich fine detail, vertical 9:16 composition, main subject in the upper two thirds, no text, no letters, no watermark, no logo. Scene: Pitch black night landscape lit only by stars | O2: Cinematic photorealistic space visualization, NASA/ESA documentary style, dramatic volumetric lighting, deep blacks, rich fine detail, vertical 9:16 composition, main subject in the upper two thirds, no text, no letters, no watermark, no logo. Scene: Earth seen from space with its axis visibly tilted and wobbling | P2: Cinematic photorealistic space visualization, NASA/ESA documentary style, dramatic volumetric lighting, deep blacks, rich fine detail, vertical 9:16 composition, main subject in the upper two thirds, no text, no letters, no watermark, no logo. Scene: Earth alone in space without its Moon, lonely composition | Q2: whoosh, deep_boom | R2: mystery | S2: Et si la Lune disparaissait ? 🌌 Tu penses qu'on survivrait sans la Lune ? #espace #etsi #science #univers #astronomie #shorts | T2: Produis la vidéo A01 « Et si la Lune disparaissait ? ». 1) Voix : ElevenLabs v3 via fal, voix narrateur FR validée, texte = colonne Script. 2) Timestamps mot à mot : Scribe v2 via fal, puis réaligne sur le texte exact du script. 3) Images : 6 × FLUX.2 [pro] en 1024×1792 avec les prompts Scène 1 à 6. 4) Mouvement : anime la Scène 1 (hook) en 5 s avec Kling image-to-video, caméra lente, sans audio. 5) Audio : SFX whoosh, deep_boom + musique « mystery » depuis la banque (-18 dB sous la voix, ducking). 6) Remotion : composition SpaceShort 1080×1920 30 fps, scènes calées sur les phrases, Ken Burns + parallaxe, sous-titres karaoké. 7) Contrôle qualité puis programmation BrightBean le J1 à 08:00 avec la légende fournie, label contenu IA activé. | U2: À produire
A3: 2 | B3: 1 | C3: =Budget!$B$4+B3-1 -> 46296 | D3: 12:30 | E3: B01 | F3: Échelle de l'univers | G3: Le Soleil est vraiment gigantesque | H3: Tu vois la Terre ? Aligne-en 109 côte à côte : tu obtiens le diamètre du Soleil. Et en volume, c'est encore plus fou : on pourrait y faire entrer environ 1,3 million de Terres. À lui seul, le Soleil représente 99,8 % de la masse de tout le Système solaire. Les planètes, les lunes, les astéroïdes ? Des miettes. Et pourtant, à l'échelle de la galaxie, c'est une étoile tout à fait moyenne. Il y en a des centaines de milliards comme lui, et certaines sont bien plus grosses. | I3: =LEN(H3) -> 474 | J3: =ROUND(I3/Budget!$B$5,0) -> 32 | K3: Cinematic photorealistic space visualization, NASA/ESA documentary style, dramatic volumetric lighting, deep blacks, rich fine detail, vertical 9:16 composition, main subject in the upper two thirds, no text, no letters, no watermark, no logo. Scene: Tiny Earth next to the enormous Sun surface | L3: Cinematic photorealistic space visualization, NASA/ESA documentary style, dramatic volumetric lighting, deep blacks, rich fine detail, vertical 9:16 composition, main subject in the upper two thirds, no text, no letters, no watermark, no logo. Scene: Row of 109 Earths spanning the Sun's diameter | M3: Cinematic photorealistic space visualization, NASA/ESA documentary style, dramatic volumetric lighting, deep blacks, rich fine detail, vertical 9:16 composition, main subject in the upper two thirds, no text, no letters, no watermark, no logo. Scene: Sun filled with countless tiny Earths, volume concept | N3: Cinematic photorealistic space visualization, NASA/ESA documentary style, dramatic volumetric lighting, deep blacks, rich fine detail, vertical 9:16 composition, main subject in the upper two thirds, no text, no letters, no watermark, no logo. Scene: Solar system with planets as crumbs beside the Sun | O3: Cinematic photorealistic space visualization, NASA/ESA documentary style, dramatic volumetric lighting, deep blacks, rich fine detail, vertical 9:16 composition, main subject in the upper two thirds, no text, no letters, no watermark, no logo. Scene: Sun as a small star among many in the Milky Way | P3: Cinematic photorealistic space visualization, NASA/ESA documentary style, dramatic volumetric lighting, deep blacks, rich fine detail, vertical 9:16 composition, main subject in the upper two thirds, no text, no letters, no watermark, no logo. Scene: Giant stars dwarfing the Sun, scale comparison | Q3: whoosh, riser | R3: epic | S3: Le Soleil est vraiment gigantesque 🌌 Tu pensais qu'il était aussi gros ? #espace #univers #astronomie #science #vertige #shorts | T3: Produis la vidéo B01 « Le Soleil est vraiment gigantesque ». 1) Voix : ElevenLabs v3 via fal, voix narrateur FR validée, texte = colonne Script. 2) Timestamps mot à mot : Scribe v2 via fal, puis réaligne sur le texte exact du script. 3) Images : 6 × FLUX.2 [pro] en 1024×1792 avec les prompts Scène 1 à 6. 4) Mouvement : anime la Scène 1 (hook) en 5 s avec Kling image-to-video, caméra lente, sans audio. 5) Audio : SFX whoosh, riser + musique « epic » depuis la banque (-18 dB sous la voix, ducking). 6) Remotion : composition SpaceShort 1080×1920 30 fps, scènes calées sur les phrases, Ken Burns + parallaxe, sous-titres karaoké. 7) Contrôle qualité puis programmation BrightBean le J1 à 12:30 avec la légende fournie, label contenu IA activé. | U3: À produire
A4: 3 | B4: 1 | C4: =Budget!$B$4+B4-1 -> 46296 | D4: 19:00 | E4: C01 | F4: Planètes & lunes | G4: Sur Vénus, un jour dure plus qu'un an | H4: Sur Vénus, un jour dure plus longtemps qu'une année. Elle met 243 jours terrestres à tourner sur elle-même, mais seulement 225 jours à faire le tour du Soleil. Et elle tourne à l'envers : là-bas, le Soleil se lève à l'ouest. En surface, il fait environ 465 degrés, assez pour faire fondre du plomb. La pression équivaut à celle qu'on subit à 900 mètres sous la mer. Les sondes soviétiques Venera qui s'y sont posées ont tenu au mieux deux heures. Vénus, c'est la jumelle infernale de la Terre. | I4: =LEN(H4) -> 493 | J4: =ROUND(I4/Budget!$B$5,0) -> 33 | K4: Cinematic photorealistic space visualization, NASA/ESA documentary style, dramatic volumetric lighting, deep blacks, rich fine detail, vertical 9:16 composition, main subject in the upper two thirds, no text, no letters, no watermark, no logo. Scene: Venus wrapped in thick yellow clouds | L4: Cinematic photorealistic space visualization, NASA/ESA documentary style, dramatic volumetric lighting, deep blacks, rich fine detail, vertical 9:16 composition, main subject in the upper two thirds, no text, no letters, no watermark, no logo. Scene: Calendar comparison: day longer than year on Venus | M4: Cinematic photorealistic space visualization, NASA/ESA documentary style, dramatic volumetric lighting, deep blacks, rich fine detail, vertical 9:16 composition, main subject in the upper two thirds, no text, no letters, no watermark, no logo. Scene: Sun rising in the west over a Venusian landscape | N4: Cinematic photorealistic space visualization, NASA/ESA documentary style, dramatic volumetric lighting, deep blacks, rich fine detail, vertical 9:16 composition, main subject in the upper two thirds, no text, no letters, no watermark, no logo. Scene: Molten lead droplets on scorching Venus rocks | O4: Cinematic photorealistic space visualization, NASA/ESA documentary style, dramatic volumetric lighting, deep blacks, rich fine detail, vertical 9:16 composition, main subject in the upper two thirds, no text, no letters, no watermark, no logo. Scene: Soviet Venera lander on orange volcanic ground | P4: Cinematic photorealistic space visualization, NASA/ESA documentary style, dramatic volumetric lighting, deep blacks, rich fine detail, vertical 9:16 composition, main subject in the upper two thirds, no text, no letters, no watermark, no logo. Scene: Earth and Venus side by side, twin planets | Q4: rumble, crackle | R4: tension | S4: Sur Vénus, un jour dure plus qu'un an 🌌 Tu savais que le Soleil s'y levait à l'ouest ? #espace #planetes #systemesolaire #astronomie #science #shorts | T4: Produis la vidéo C01 « Sur Vénus, un jour dure plus qu'un an ». 1) Voix : ElevenLabs v3 via fal, voix narrateur FR validée, texte = colonne Script. 2) Timestamps mot à mot : Scribe v2 via fal, puis réaligne sur le texte exact du script. 3) Images : 6 × FLUX.2 [pro] en 1024×1792 avec les prompts Scène 1 à 6. 4) Mouvement : anime la Scène 1 (hook) en 5 s avec Kling image-to-video, caméra lente, sans audio. 5) Audio : SFX rumble, crackle + musique « tension » depuis la banque (-18 dB sous la voix, ducking). 6) Remotion : composition SpaceShort 1080×1920 30 fps, scènes calées sur les phrases, Ken Burns + parallaxe, sous-titres karaoké. 7) Contrôle qualité puis programmation BrightBean le J1 à 19:00 avec la légende fournie, label contenu IA activé. | U4: À produire
A5: 4 | B5: 2 | C5: =Budget!$B$4+B5-1 -> 46297 | D5: 08:00 | E5: D01 | F5: Étoiles & trous noirs | G5: Comment naît une étoile | H5: Une étoile commence comme un nuage froid de gaz et de poussière. Un nuage immense, parfois sur des dizaines d'années-lumière. Un jour, une partie s'effondre sous son propre poids. Le cœur se compresse, chauffe, tourne de plus en plus vite. Quand il atteint environ 10 millions de degrés, la fusion nucléaire démarre : l'hydrogène devient de l'hélium. Une étoile est née. Autour, un disque de matière qui formera peut-être des planètes. C'est exactement ce qui est arrivé au Soleil, il y a 4,6 milliards d'années. | I5: =LEN(H5) -> 512 | J5: =ROUND(I5/Budget!$B$5,0) -> 34 | K5: Cinematic photorealistic space visualization, NASA/ESA documentary style, dramatic volumetric lighting, deep blacks, rich fine detail, vertical 9:16 composition, main subject in the upper two thirds, no text, no letters, no watermark, no logo. Scene: Vast cold nebula of gas and dust | L5: Cinematic photorealistic space visualization, NASA/ESA documentary style, dramatic volumetric lighting, deep blacks, rich fine detail, vertical 9:16 composition, main subject in the upper two thirds, no text, no letters, no watermark, no logo. Scene: Dense knot collapsing inside the nebula | M5: Cinematic photorealistic space visualization, NASA/ESA documentary style, dramatic volumetric lighting, deep blacks, rich fine detail, vertical 9:16 composition, main subject in the upper two thirds, no text, no letters, no watermark, no logo. Scene: Spinning protostar with jets | N5: Cinematic photorealistic space visualization, NASA/ESA documentary style, dramatic volumetric lighting, deep blacks, rich fine detail, vertical 9:16 composition, main subject in the upper two thirds, no text, no letters, no watermark, no logo. Scene: Core igniting with nuclear fusion glow | O5: Cinematic photorealistic space visualization, NASA/ESA documentary style, dramatic volumetric lighting, deep blacks, rich fine detail, vertical 9:16 composition, main subject in the upper two thirds, no text, no letters, no watermark, no logo. Scene: Protoplanetary disk around a newborn star | P5: Cinematic photorealistic space visualization, NASA/ESA documentary style, dramatic volumetric lighting, deep blacks, rich fine detail, vertical 9:16 composition, main subject in the upper two thirds, no text, no letters, no watermark, no logo. Scene: Young Sun with forming planets | Q5: riser, deep_boom | R5: wonder | S5: Comment naît une étoile 🌌 Tu imaginais une naissance aussi longue ? #espace #trounoir #etoiles #astrophysique #science #shorts | T5: Produis la vidéo D01 « Comment naît une étoile ». 1) Voix : ElevenLabs v3 via fal, voix narrateur FR validée, texte = colonne Script. 2) Timestamps mot à mot : Scribe v2 via fal, puis réaligne sur le texte exact du script. 3) Images : 6 × FLUX.2 [pro] en 1024×1792 avec les prompts Scène 1 à 6. 4) Mouvement : anime la Scène 1 (hook) en 5 s avec Kling image-to-video, caméra lente, sans audio. 5) Audio : SFX riser, deep_boom + musique « wonder » depuis la banque (-18 dB sous la voix, ducking). 6) Remotion : composition SpaceShort 1080×1920 30 fps, scènes calées sur les phrases, Ken Burns + parallaxe, sous-titres karaoké. 7) Contrôle qualité puis programmation BrightBean le J2 à 08:00 avec la légende fournie, label contenu IA activé. | U5: À produire
A6: 5 | B6: 2 | C6: =Budget!$B$4+B6-1 -> 46297 | D6: 12:30 | E6: E01 | F6: Histoire de la conquête spatiale | G6: Spoutnik, le bip qui a changé le monde | H6: 4 octobre 1957. L'Union soviétique lance Spoutnik 1. Une sphère métallique de 58 centimètres, avec quatre antennes. Elle ne fait qu'une chose : émettre un bip radio. Mais ce bip, n'importe quel radioamateur peut le capter. Pour les États-Unis, c'est un choc. Les Soviétiques sont en avance. Moins d'un an plus tard naît la NASA. Spoutnik a tourné autour de la Terre pendant environ trois mois avant de se consumer dans l'atmosphère. Un simple bip venait de lancer la course à l'espace. | I6: =LEN(H6) -> 485 | J6: =ROUND(I6/Budget!$B$5,0) -> 32 | K6: Cinematic historical recreation, 1950s-1970s space age atmosphere, subtle film grain, warm archival color grading, photorealistic, vertical 9:16 composition, main subject in the upper two thirds, no text, no letters, no watermark, no logo, no real identifiable faces. Scene: Sputnik 1 shiny sphere with four antennas in orbit | L6: Cinematic historical recreation, 1950s-1970s space age atmosphere, subtle film grain, warm archival color grading, photorealistic, vertical 9:16 composition, main subject in the upper two thirds, no text, no letters, no watermark, no logo, no real identifiable faces. Scene: Soviet rocket launch at night, 1957 retro | M6: Cinematic historical recreation, 1950s-1970s space age atmosphere, subtle film grain, warm archival color grading, photorealistic, vertical 9:16 composition, main subject in the upper two thirds, no text, no letters, no watermark, no logo, no real identifiable faces. Scene: Radio amateur listening with headphones, vintage room | N6: Cinematic historical recreation, 1950s-1970s space age atmosphere, subtle film grain, warm archival color grading, photorealistic, vertical 9:16 composition, main subject in the upper two thirds, no text, no letters, no watermark, no logo, no real identifiable faces. Scene: 1950s newspaper headlines concept, no readable text | O6: Cinematic historical recreation, 1950s-1970s space age atmosphere, subtle film grain, warm archival color grading, photorealistic, vertical 9:16 composition, main subject in the upper two thirds, no text, no letters, no watermark, no logo, no real identifiable faces. Scene: NASA founding era rocket hangar, retro | P6: Cinematic historical recreation, 1950s-1970s space age atmosphere, subtle film grain, warm archival color grading, photorealistic, vertical 9:16 composition, main subject in the upper two thirds, no text, no letters, no watermark, no logo, no real identifiable faces. Scene: Sputnik burning up in the atmosphere | Q6: beep, launch | R6: retro | S6: Spoutnik, le bip qui a changé le monde 🌌 Tu savais que n'importe qui pouvait capter le bip ? #espace #histoire #conquetespatiale #nasa #science #shorts | T6: Produis la vidéo E01 « Spoutnik, le bip qui a changé le monde ». 1) Voix : ElevenLabs v3 via fal, voix narrateur FR validée, texte = colonne Script. 2) Timestamps mot à mot : Scribe v2 via fal, puis réaligne sur le texte exact du script. 3) Images : 6 × FLUX.2 [pro] en 1024×1792 avec les prompts Scène 1 à 6. 4) Mouvement : anime la Scène 1 (hook) en 5 s avec Kling image-to-video, caméra lente, sans audio. 5) Audio : SFX beep, launch + musique « retro » depuis la banque (-18 dB sous la voix, ducking). 6) Remotion : composition SpaceShort 1080×1920 30 fps, scènes calées sur les phrases, Ken Burns + parallaxe, sous-titres karaoké. 7) Contrôle qualité puis programmation BrightBean le J2 à 12:30 avec la légende fournie, label contenu IA activé. | U6: À produire
A7: 6 | B7: 2 | C7: =Budget!$B$4+B7-1 -> 46297 | D7: 19:00 | E7: F01 | F7: Idées reçues | G7: Il n'y a pas de gravité dans l'ISS ? Faux | H7: Les astronautes flottent dans l'ISS parce qu'il n'y a pas de gravité ? Faux. À 400 km d'altitude, la gravité est encore d'environ 90 % de celle au sol. Alors pourquoi ils flottent ? Parce qu'ils sont en chute libre permanente. La station tombe vers la Terre... mais elle va tellement vite, près de 28 000 km/h, qu'elle rate le sol en permanence. Elle tombe autour de la Terre. Et comme les astronautes tombent à la même vitesse que la station, ils flottent. L'orbite, c'est une chute infinie. | I7: =LEN(H7) -> 492 | J7: =ROUND(I7/Budget!$B$5,0) -> 33 | K7: Cinematic photorealistic space visualization, NASA/ESA documentary style, dramatic volumetric lighting, deep blacks, rich fine detail, vertical 9:16 composition, main subject in the upper two thirds, no text, no letters, no watermark, no logo. Scene: Astronaut floating inside the ISS | L7: Cinematic photorealistic space visualization, NASA/ESA documentary style, dramatic volumetric lighting, deep blacks, rich fine detail, vertical 9:16 composition, main subject in the upper two thirds, no text, no letters, no watermark, no logo. Scene: Gravity arrows still strong at orbital altitude | M7: Cinematic photorealistic space visualization, NASA/ESA documentary style, dramatic volumetric lighting, deep blacks, rich fine detail, vertical 9:16 composition, main subject in the upper two thirds, no text, no letters, no watermark, no logo. Scene: ISS falling around Earth, curved path | N7: Cinematic photorealistic space visualization, NASA/ESA documentary style, dramatic volumetric lighting, deep blacks, rich fine detail, vertical 9:16 composition, main subject in the upper two thirds, no text, no letters, no watermark, no logo. Scene: Cannonball thought experiment from a mountain | O7: Cinematic photorealistic space visualization, NASA/ESA documentary style, dramatic volumetric lighting, deep blacks, rich fine detail, vertical 9:16 composition, main subject in the upper two thirds, no text, no letters, no watermark, no logo. Scene: Astronaut and station falling together, concept | P7: Cinematic photorealistic space visualization, NASA/ESA documentary style, dramatic volumetric lighting, deep blacks, rich fine detail, vertical 9:16 composition, main subject in the upper two thirds, no text, no letters, no watermark, no logo. Scene: ISS over Earth horizon | Q7: whoosh, chime | R7: calm | S7: Il n'y a pas de gravité dans l'ISS ? Faux 🌌 Tu pensais qu'il n'y avait pas de gravité ? #espace #idéesreçues #science #astronomie #lesavaistu #shorts | T7: Produis la vidéo F01 « Il n'y a pas de gravité dans l'ISS ? Faux ». 1) Voix : ElevenLabs v3 via fal, voix narrateur FR validée, texte = colonne Script. 2) Timestamps mot à mot : Scribe v2 via fal, puis réaligne sur le texte exact du script. 3) Images : 6 × FLUX.2 [pro] en 1024×1792 avec les prompts Scène 1 à 6. 4) Mouvement : anime la Scène 1 (hook) en 5 s avec Kling image-to-video, caméra lente, sans audio. 5) Audio : SFX whoosh, chime + musique « calm » depuis la banque (-18 dB sous la voix, ducking). 6) Remotion : composition SpaceShort 1080×1920 30 fps, scènes calées sur les phrases, Ken Burns + parallaxe, sous-titres karaoké. 7) Contrôle qualité puis programmation BrightBean le J2 à 19:00 avec la légende fournie, label contenu IA activé. | U7: À produire
A8: 7 | B8: 3 | C8: =Budget!$B$4+B8-1 -> 46298 | D8: 08:00 | E8: A02 | F8: Et si… ? | G8: Et si la Terre arrêtait de tourner ? | H8: À l'équateur, tu tournes en ce moment à environ 1 670 km/h. Sans le sentir. Maintenant, imagine que la Terre s'arrête net. Toi, l'air, les océans, vous continuez à avancer à cette vitesse. Des vents plus violents que n'importe quel ouragan, des vagues gigantesques. Et si l'arrêt était progressif ? Les océans migreraient vers les pôles, laissant un immense continent à l'équateur. Un jour durerait un an entier : six mois de lumière brûlante, six mois de nuit glaciale. Heureusement, rien ne peut arrêter la Terre comme ça. | I8: =LEN(H8) -> 524 | J8: =ROUND(I8/Budget!$B$5,0) -> 35 | K8: Cinematic photorealistic space visualization, NASA/ESA documentary style, dramatic volumetric lighting, deep blacks, rich fine detail, vertical 9:16 composition, main subject in the upper two thirds, no text, no letters, no watermark, no logo. Scene: Earth spinning in space with motion trails at the equator | L8: Cinematic photorealistic space visualization, NASA/ESA documentary style, dramatic volumetric lighting, deep blacks, rich fine detail, vertical 9:16 composition, main subject in the upper two thirds, no text, no letters, no watermark, no logo. Scene: City skyline hit by a gigantic wall of wind and debris | M8: Cinematic photorealistic space visualization, NASA/ESA documentary style, dramatic volumetric lighting, deep blacks, rich fine detail, vertical 9:16 composition, main subject in the upper two thirds, no text, no letters, no watermark, no logo. Scene: Colossal tsunami wave rising over a coastline | N8: Cinematic photorealistic space visualization, NASA/ESA documentary style, dramatic volumetric lighting, deep blacks, rich fine detail, vertical 9:16 composition, main subject in the upper two thirds, no text, no letters, no watermark, no logo. Scene: Globe with oceans pooled at both poles and a bare equatorial continent | O8: Cinematic photorealistic space visualization, NASA/ESA documentary style, dramatic volumetric lighting, deep blacks, rich fine detail, vertical 9:16 composition, main subject in the upper two thirds, no text, no letters, no watermark, no logo. Scene: Scorched desert under a motionless blazing sun | P8: Cinematic photorealistic space visualization, NASA/ESA documentary style, dramatic volumetric lighting, deep blacks, rich fine detail, vertical 9:16 composition, main subject in the upper two thirds, no text, no letters, no watermark, no logo. Scene: Frozen night side of Earth under stars | Q8: rumble, whoosh, deep_boom | R8: tension | S8: Et si la Terre arrêtait de tourner ? 🌌 Tu choisirais le côté jour ou le côté nuit ? #espace #etsi #science #univers #astronomie #shorts | T8: Produis la vidéo A02 « Et si la Terre arrêtait de tourner ? ». 1) Voix : ElevenLabs v3 via fal, voix narrateur FR validée, texte = colonne Script. 2) Timestamps mot à mot : Scribe v2 via fal, puis réaligne sur le texte exact du script. 3) Images : 6 × FLUX.2 [pro] en 1024×1792 avec les prompts Scène 1 à 6. 4) Mouvement : anime la Scène 1 (hook) en 5 s avec Kling image-to-video, caméra lente, sans audio. 5) Audio : SFX rumble, whoosh, deep_boom + musique « tension » depuis la banque (-18 dB sous la voix, ducking). 6) Remotion : composition SpaceShort 1080×1920 30 fps, scènes calées sur les phrases, Ken Burns + parallaxe, sous-titres karaoké. 7) Contrôle qualité puis programmation BrightBean le J3 à 08:00 avec la légende fournie, label contenu IA activé. | U8: À produire
A9: 8 | B9: 3 | C9: =Budget!$B$4+B9-1 -> 46298 | D9: 12:30 | E9: B02 | F9: Échelle de l'univers | G9: L'étoile la plus grosse qu'on connaisse | H9: Si tu mettais Stephenson 2-18 à la place du Soleil, sa surface dépasserait peut-être l'orbite de Saturne. Cette supergéante rouge ferait environ 2 000 fois le rayon du Soleil, selon certaines estimations. On reste prudents : mesurer une étoile aussi lointaine, c'est très difficile. Un avion de ligne mettrait des siècles à en faire le tour. Et pourtant, elle est beaucoup moins massive que sa taille le laisse croire. C'est un ballon gigantesque, gonflé, en fin de vie. Un jour, elle explosera. | I9: =LEN(H9) -> 495 | J9: =ROUND(I9/Budget!$B$5,0) -> 33 | K9: Cinematic photorealistic space visualization, NASA/ESA documentary style, dramatic volumetric lighting, deep blacks, rich fine detail, vertical 9:16 composition, main subject in the upper two thirds, no text, no letters, no watermark, no logo. Scene: Enormous red supergiant star filling the frame | L9: Cinematic photorealistic space visualization, NASA/ESA documentary style, dramatic volumetric lighting, deep blacks, rich fine detail, vertical 9:16 composition, main subject in the upper two thirds, no text, no letters, no watermark, no logo. Scene: Solar system orbits inside a red supergiant outline | M9: Cinematic photorealistic space visualization, NASA/ESA documentary style, dramatic volumetric lighting, deep blacks, rich fine detail, vertical 9:16 composition, main subject in the upper two thirds, no text, no letters, no watermark, no logo. Scene: Scale: Sun as a tiny dot next to a supergiant | N9: Cinematic photorealistic space visualization, NASA/ESA documentary style, dramatic volumetric lighting, deep blacks, rich fine detail, vertical 9:16 composition, main subject in the upper two thirds, no text, no letters, no watermark, no logo. Scene: Airplane circling a colossal star, whimsical scale | O9: Cinematic photorealistic space visualization, NASA/ESA documentary style, dramatic volumetric lighting, deep blacks, rich fine detail, vertical 9:16 composition, main subject in the upper two thirds, no text, no letters, no watermark, no logo. Scene: Diffuse glowing outer layers of a supergiant | P9: Cinematic photorealistic space visualization, NASA/ESA documentary style, dramatic volumetric lighting, deep blacks, rich fine detail, vertical 9:16 composition, main subject in the upper two thirds, no text, no letters, no watermark, no logo. Scene: Supergiant star beginning to collapse | Q9: riser, deep_boom | R9: epic | S9: L'étoile la plus grosse qu'on connaisse 🌌 Tu connaissais cette étoile ? #espace #univers #astronomie #science #vertige #shorts | T9: Produis la vidéo B02 « L'étoile la plus grosse qu'on connaisse ». 1) Voix : ElevenLabs v3 via fal, voix narrateur FR validée, texte = colonne Script. 2) Timestamps mot à mot : Scribe v2 via fal, puis réaligne sur le texte exact du script. 3) Images : 6 × FLUX.2 [pro] en 1024×1792 avec les prompts Scène 1 à 6. 4) Mouvement : anime la Scène 1 (hook) en 5 s avec Kling image-to-video, caméra lente, sans audio. 5) Audio : SFX riser, deep_boom + musique « epic » depuis la banque (-18 dB sous la voix, ducking). 6) Remotion : composition SpaceShort 1080×1920 30 fps, scènes calées sur les phrases, Ken Burns + parallaxe, sous-titres karaoké. 7) Contrôle qualité puis programmation BrightBean le J3 à 12:30 avec la légende fournie, label contenu IA activé. | U9: À produire
A10: 9 | B10: 3 | C10: =Budget!$B$4+B10-1 -> 46298 | D10: 19:00 | E10: C02 | F10: Planètes & lunes | G10: Uranus roule sur le côté | H10: Uranus est couchée sur le côté. Son axe est incliné d'environ 98 degrés : elle roule autour du Soleil comme une boule de bowling. Conséquence : ses saisons sont extrêmes. Une année sur Uranus dure 84 ans. Chaque pôle passe environ 42 ans en plein jour, puis 42 ans dans la nuit. Pourquoi une telle inclinaison ? L'hypothèse la plus répandue : une collision géante avec un corps de la taille de la Terre, il y a très longtemps. Une seule sonde l'a visitée : Voyager 2, en 1986. | I10: =LEN(H10) -> 476 | J10: =ROUND(I10/Budget!$B$5,0) -> 32 | K10: Cinematic photorealistic space visualization, NASA/ESA documentary style, dramatic volumetric lighting, deep blacks, rich fine detail, vertical 9:16 composition, main subject in the upper two thirds, no text, no letters, no watermark, no logo. Scene: Uranus tilted on its side with faint rings | L10: Cinematic photorealistic space visualization, NASA/ESA documentary style, dramatic volumetric lighting, deep blacks, rich fine detail, vertical 9:16 composition, main subject in the upper two thirds, no text, no letters, no watermark, no logo. Scene: Uranus rolling along its orbit like a ball | M10: Cinematic photorealistic space visualization, NASA/ESA documentary style, dramatic volumetric lighting, deep blacks, rich fine detail, vertical 9:16 composition, main subject in the upper two thirds, no text, no letters, no watermark, no logo. Scene: Pole of Uranus in endless daylight | N10: Cinematic photorealistic space visualization, NASA/ESA documentary style, dramatic volumetric lighting, deep blacks, rich fine detail, vertical 9:16 composition, main subject in the upper two thirds, no text, no letters, no watermark, no logo. Scene: Same pole in long darkness | O10: Cinematic photorealistic space visualization, NASA/ESA documentary style, dramatic volumetric lighting, deep blacks, rich fine detail, vertical 9:16 composition, main subject in the upper two thirds, no text, no letters, no watermark, no logo. Scene: Giant impact with young Uranus | P10: Cinematic photorealistic space visualization, NASA/ESA documentary style, dramatic volumetric lighting, deep blacks, rich fine detail, vertical 9:16 composition, main subject in the upper two thirds, no text, no letters, no watermark, no logo. Scene: Voyager 2 flying past Uranus | Q10: whoosh, deep_boom | R10: mystery | S10: Uranus roule sur le côté 🌌 42 ans de jour, 42 ans de nuit. Tu tiendrais ? #espace #planetes #systemesolaire #astronomie #science #shorts | T10: Produis la vidéo C02 « Uranus roule sur le côté ». 1) Voix : ElevenLabs v3 via fal, voix narrateur FR validée, texte = colonne Script. 2) Timestamps mot à mot : Scribe v2 via fal, puis réaligne sur le texte exact du script. 3) Images : 6 × FLUX.2 [pro] en 1024×1792 avec les prompts Scène 1 à 6. 4) Mouvement : anime la Scène 1 (hook) en 5 s avec Kling image-to-video, caméra lente, sans audio. 5) Audio : SFX whoosh, deep_boom + musique « mystery » depuis la banque (-18 dB sous la voix, ducking). 6) Remotion : composition SpaceShort 1080×1920 30 fps, scènes calées sur les phrases, Ken Burns + parallaxe, sous-titres karaoké. 7) Contrôle qualité puis programmation BrightBean le J3 à 19:00 avec la légende fournie, label contenu IA activé. | U10: À produire
A11: 10 | B11: 4 | C11: =Budget!$B$4+B11-1 -> 46299 | D11: 08:00 | E11: D02 | F11: Étoiles & trous noirs | G11: Comment va mourir le Soleil | H11: Le Soleil a environ 4,6 milliards d'années. Il est à peu près à la moitié de sa vie. Dans environ 5 milliards d'années, il manquera d'hydrogène dans son cœur. Il va gonfler et devenir une géante rouge. Mercure et Vénus seront avalées. La Terre ? Peut-être aussi, les modèles hésitent. Puis il expulsera ses couches externes en une magnifique nébuleuse. Au centre, il restera une naine blanche, de la taille de la Terre, qui refroidira pendant des milliards d'années. Pas d'explosion, il est trop petit pour ça. | I11: =LEN(H11) -> 510 | J11: =ROUND(I11/Budget!$B$5,0) -> 34 | K11: Cinematic photorealistic space visualization, NASA/ESA documentary style, dramatic volumetric lighting, deep blacks, rich fine detail, vertical 9:16 composition, main subject in the upper two thirds, no text, no letters, no watermark, no logo. Scene: Sun at midlife, calm and bright | L11: Cinematic photorealistic space visualization, NASA/ESA documentary style, dramatic volumetric lighting, deep blacks, rich fine detail, vertical 9:16 composition, main subject in the upper two thirds, no text, no letters, no watermark, no logo. Scene: Sun swelling into a red giant | M11: Cinematic photorealistic space visualization, NASA/ESA documentary style, dramatic volumetric lighting, deep blacks, rich fine detail, vertical 9:16 composition, main subject in the upper two thirds, no text, no letters, no watermark, no logo. Scene: Red giant engulfing inner planets | N11: Cinematic photorealistic space visualization, NASA/ESA documentary style, dramatic volumetric lighting, deep blacks, rich fine detail, vertical 9:16 composition, main subject in the upper two thirds, no text, no letters, no watermark, no logo. Scene: Scorched Earth under a giant red sun | O11: Cinematic photorealistic space visualization, NASA/ESA documentary style, dramatic volumetric lighting, deep blacks, rich fine detail, vertical 9:16 composition, main subject in the upper two thirds, no text, no letters, no watermark, no logo. Scene: Colorful planetary nebula shell | P11: Cinematic photorealistic space visualization, NASA/ESA documentary style, dramatic volumetric lighting, deep blacks, rich fine detail, vertical 9:16 composition, main subject in the upper two thirds, no text, no letters, no watermark, no logo. Scene: Tiny white dwarf at the center | Q11: rumble, riser | R11: mystery | S11: Comment va mourir le Soleil 🌌 5 milliards d'années, ça te rassure ? #espace #trounoir #etoiles #astrophysique #science #shorts | T11: Produis la vidéo D02 « Comment va mourir le Soleil ». 1) Voix : ElevenLabs v3 via fal, voix narrateur FR validée, texte = colonne Script. 2) Timestamps mot à mot : Scribe v2 via fal, puis réaligne sur le texte exact du script. 3) Images : 6 × FLUX.2 [pro] en 1024×1792 avec les prompts Scène 1 à 6. 4) Mouvement : anime la Scène 1 (hook) en 5 s avec Kling image-to-video, caméra lente, sans audio. 5) Audio : SFX rumble, riser + musique « mystery » depuis la banque (-18 dB sous la voix, ducking). 6) Remotion : composition SpaceShort 1080×1920 30 fps, scènes calées sur les phrases, Ken Burns + parallaxe, sous-titres karaoké. 7) Contrôle qualité puis programmation BrightBean le J4 à 08:00 avec la légende fournie, label contenu IA activé. | U11: À produire
A12: 11 | B12: 4 | C12: =Budget!$B$4+B12-1 -> 46299 | D12: 12:30 | E12: E02 | F12: Histoire de la conquête spatiale | G12: Laïka, première passagère de l'orbite | H12: Novembre 1957, un mois après Spoutnik 1. L'URSS envoie un être vivant en orbite : Laïka, une chienne des rues de Moscou. Elle devient le premier animal à faire le tour de la Terre. Mais la mission n'avait pas de retour prévu. Et on a appris bien plus tard qu'elle était morte quelques heures après le lancement, à cause de la surchauffe de la capsule. Son vol a prouvé qu'un organisme vivant pouvait supporter le lancement et l'apesanteur. Elle a ouvert la voie aux humains. Aujourd'hui, un monument lui rend hommage à Moscou. | I12: =LEN(H12) -> 526 | J12: =ROUND(I12/Budget!$B$5,0) -> 35 | K12: Cinematic historical recreation, 1950s-1970s space age atmosphere, subtle film grain, warm archival color grading, photorealistic, vertical 9:16 composition, main subject in the upper two thirds, no text, no letters, no watermark, no logo, no real identifiable faces. Scene: Portrait of a small mixed-breed dog, dignified, vintage tones | L12: Cinematic historical recreation, 1950s-1970s space age atmosphere, subtle film grain, warm archival color grading, photorealistic, vertical 9:16 composition, main subject in the upper two thirds, no text, no letters, no watermark, no logo, no real identifiable faces. Scene: Sputnik 2 capsule in orbit above Earth | M12: Cinematic historical recreation, 1950s-1970s space age atmosphere, subtle film grain, warm archival color grading, photorealistic, vertical 9:16 composition, main subject in the upper two thirds, no text, no letters, no watermark, no logo, no real identifiable faces. Scene: Moscow street in the 1950s, retro | N12: Cinematic historical recreation, 1950s-1970s space age atmosphere, subtle film grain, warm archival color grading, photorealistic, vertical 9:16 composition, main subject in the upper two thirds, no text, no letters, no watermark, no logo, no real identifiable faces. Scene: Dog silhouette against Earth from orbit, respectful | O12: Cinematic historical recreation, 1950s-1970s space age atmosphere, subtle film grain, warm archival color grading, photorealistic, vertical 9:16 composition, main subject in the upper two thirds, no text, no letters, no watermark, no logo, no real identifiable faces. Scene: Scientists in a 1950s control room | P12: Cinematic historical recreation, 1950s-1970s space age atmosphere, subtle film grain, warm archival color grading, photorealistic, vertical 9:16 composition, main subject in the upper two thirds, no text, no letters, no watermark, no logo, no real identifiable faces. Scene: Commemorative monument with a dog on a rocket, respectful | Q12: beep | R12: calm | S12: Laïka, première passagère de l'orbite 🌌 Tu connaissais son histoire ? #espace #histoire #conquetespatiale #nasa #science #shorts | T12: Produis la vidéo E02 « Laïka, première passagère de l'orbite ». 1) Voix : ElevenLabs v3 via fal, voix narrateur FR validée, texte = colonne Script. 2) Timestamps mot à mot : Scribe v2 via fal, puis réaligne sur le texte exact du script. 3) Images : 6 × FLUX.2 [pro] en 1024×1792 avec les prompts Scène 1 à 6. 4) Mouvement : anime la Scène 1 (hook) en 5 s avec Kling image-to-video, caméra lente, sans audio. 5) Audio : SFX beep + musique « calm » depuis la banque (-18 dB sous la voix, ducking). 6) Remotion : composition SpaceShort 1080×1920 30 fps, scènes calées sur les phrases, Ken Burns + parallaxe, sous-titres karaoké. 7) Contrôle qualité puis programmation BrightBean le J4 à 12:30 avec la légende fournie, label contenu IA activé. | U12: À produire
A13: 12 | B13: 4 | C13: =Budget!$B$4+B13-1 -> 46299 | D13: 19:00 | E13: F02 | F13: Idées reçues | G13: La face cachée de la Lune n'est pas sombre | H13: La face cachée de la Lune n'est pas la face sombre. Elle reçoit autant de soleil que l'autre. Elle est juste cachée... pour nous. La Lune met exactement le même temps à tourner sur elle-même qu'à tourner autour de la Terre. Du coup, elle nous montre toujours la même face. Pendant la nouvelle lune, quand on ne voit rien, c'est justement la face cachée qui est en plein soleil. Et en 2019, la sonde chinoise Chang'e 4 est devenue le premier engin à s'y poser en douceur. | I13: =LEN(H13) -> 470 | J13: =ROUND(I13/Budget!$B$5,0) -> 31 | K13: Cinematic photorealistic space visualization, NASA/ESA documentary style, dramatic volumetric lighting, deep blacks, rich fine detail, vertical 9:16 composition, main subject in the upper two thirds, no text, no letters, no watermark, no logo. Scene: Far side of the Moon brightly lit by the Sun | L13: Cinematic photorealistic space visualization, NASA/ESA documentary style, dramatic volumetric lighting, deep blacks, rich fine detail, vertical 9:16 composition, main subject in the upper two thirds, no text, no letters, no watermark, no logo. Scene: Moon rotating while orbiting Earth, same face | M13: Cinematic photorealistic space visualization, NASA/ESA documentary style, dramatic volumetric lighting, deep blacks, rich fine detail, vertical 9:16 composition, main subject in the upper two thirds, no text, no letters, no watermark, no logo. Scene: New moon phase with far side illuminated | N13: Cinematic photorealistic space visualization, NASA/ESA documentary style, dramatic volumetric lighting, deep blacks, rich fine detail, vertical 9:16 composition, main subject in the upper two thirds, no text, no letters, no watermark, no logo. Scene: Cratered far side terrain close-up | O13: Cinematic photorealistic space visualization, NASA/ESA documentary style, dramatic volumetric lighting, deep blacks, rich fine detail, vertical 9:16 composition, main subject in the upper two thirds, no text, no letters, no watermark, no logo. Scene: Chang'e 4 lander on lunar far side | P13: Cinematic photorealistic space visualization, NASA/ESA documentary style, dramatic volumetric lighting, deep blacks, rich fine detail, vertical 9:16 composition, main subject in the upper two thirds, no text, no letters, no watermark, no logo. Scene: Earth-facing near side with dark maria | Q13: whoosh, chime | R13: calm | S13: La face cachée de la Lune n'est pas sombre 🌌 Tu disais 'face sombre' toi aussi ? #espace #idéesreçues #science #astronomie #lesavaistu #shorts | T13: Produis la vidéo F02 « La face cachée de la Lune n'est pas sombre ». 1) Voix : ElevenLabs v3 via fal, voix narrateur FR validée, texte = colonne Script. 2) Timestamps mot à mot : Scribe v2 via fal, puis réaligne sur le texte exact du script. 3) Images : 6 × FLUX.2 [pro] en 1024×1792 avec les prompts Scène 1 à 6. 4) Mouvement : anime la Scène 1 (hook) en 5 s avec Kling image-to-video, caméra lente, sans audio. 5) Audio : SFX whoosh, chime + musique « calm » depuis la banque (-18 dB sous la voix, ducking). 6) Remotion : composition SpaceShort 1080×1920 30 fps, scènes calées sur les phrases, Ken Burns + parallaxe, sous-titres karaoké. 7) Contrôle qualité puis programmation BrightBean le J4 à 19:00 avec la légende fournie, label contenu IA activé. | U13: À produire
... A91: 90 | B91: 30 | C91: =Budget!$B$4+B91-1 -> 46325 | D91: 19:00 | E91: F15 | F91: Idées reçues | G91: La ceinture d'astéroïdes est presque vide | H91: Dans les films, les vaisseaux zigzaguent entre des astéroïdes serrés. En réalité, la ceinture d'astéroïdes est presque vide. Il y a des millions d'astéroïdes, mais répartis sur un espace immense. Entre deux gros astéroïdes, il y a souvent des centaines de milliers de kilomètres. Si tu étais sur l'un d'eux, tu ne verrais probablement pas le suivant à l'œil nu. Les sondes qui la traversent n'ont pas besoin de l'esquiver. Et toute sa masse réunie fait moins que 5 % de notre Lune. | I91: =LEN(H91) -> 481 | J91: =ROUND(I91/Budget!$B$5,0) -> 32 | K91: Cinematic photorealistic space visualization, NASA/ESA documentary style, dramatic volumetric lighting, deep blacks, rich fine detail, vertical 9:16 composition, main subject in the upper two thirds, no text, no letters, no watermark, no logo. Scene: Movie-style crowded asteroid field, myth framing | L91: Cinematic photorealistic space visualization, NASA/ESA documentary style, dramatic volumetric lighting, deep blacks, rich fine detail, vertical 9:16 composition, main subject in the upper two thirds, no text, no letters, no watermark, no logo. Scene: Realistic asteroid belt: sparse, huge distances | M91: Cinematic photorealistic space visualization, NASA/ESA documentary style, dramatic volumetric lighting, deep blacks, rich fine detail, vertical 9:16 composition, main subject in the upper two thirds, no text, no letters, no watermark, no logo. Scene: Lone asteroid with empty space around | N91: Cinematic photorealistic space visualization, NASA/ESA documentary style, dramatic volumetric lighting, deep blacks, rich fine detail, vertical 9:16 composition, main subject in the upper two thirds, no text, no letters, no watermark, no logo. Scene: Spacecraft cruising calmly through the belt | O91: Cinematic photorealistic space visualization, NASA/ESA documentary style, dramatic volumetric lighting, deep blacks, rich fine detail, vertical 9:16 composition, main subject in the upper two thirds, no text, no letters, no watermark, no logo. Scene: Ceres dwarf planet in the belt | P91: Cinematic photorealistic space visualization, NASA/ESA documentary style, dramatic volumetric lighting, deep blacks, rich fine detail, vertical 9:16 composition, main subject in the upper two thirds, no text, no letters, no watermark, no logo. Scene: All asteroids combined into a small sphere next to the Moon | Q91: whoosh | R91: calm | S91: La ceinture d'astéroïdes est presque vide 🌌 Merci Hollywood, non ? #espace #idéesreçues #science #astronomie #lesavaistu #shorts | T91: Produis la vidéo F15 « La ceinture d'astéroïdes est presque vide ». 1) Voix : ElevenLabs v3 via fal, voix narrateur FR validée, texte = colonne Script. 2) Timestamps mot à mot : Scribe v2 via fal, puis réaligne sur le texte exact du script. 3) Images : 6 × FLUX.2 [pro] en 1024×1792 avec les prompts Scène 1 à 6. 4) Mouvement : anime la Scène 1 (hook) en 5 s avec Kling image-to-video, caméra lente, sans audio. 5) Audio : SFX whoosh + musique « calm » depuis la banque (-18 dB sous la voix, ducking). 6) Remotion : composition SpaceShort 1080×1920 30 fps, scènes calées sur les phrases, Ken Burns + parallaxe, sous-titres karaoké. 7) Contrôle qualité puis programmation BrightBean le J30 à 19:00 avec la légende fournie, label contenu IA activé. | U91: À produire

Sheet Budget
A1: Budget par vidéo (USD, prix fal.ai relevés fin sept. 2026)
A3: Paramètres généraux | B3: Valeur | F3: Source / hypothèse
A4: Date de la 1re publication | B4: 46296 | F4: À adapter.
A5: Débit de lecture de la voix (caractères / seconde) | B5: 15 | F5: Hypothèse : narration FR dynamique ~14-16 car/s.
A6: Nombre moyen de caractères par script | B6: =ROUND(AVERAGE(Calendrier!I2:I91),0) -> 493 | F6: Calculé depuis le Calendrier.
A7: Durée moyenne d'une vidéo (minutes) | B7: =B6/B5/60 -> 0.54777778 | F7: Calculé.
A8: Vidéos par jour | B8: 3 | F8: Ton objectif.
A9: Jours dans le plan | B9: 30 | F9: 90 vidéos.
A10: Marge de régénération (images ratées, reprises voix) | B10: 0.3 | F10: Hypothèse : +30 % de générations pour les ratés.
A11: Taux USD → EUR | B11: 0.86 | F11: Hypothèse à mettre à jour avec le cours du jour.
A13: Hypothèses par formule | B13: Éco | C13: Standard | D13: Premium | F13: Source / hypothèse
A14: Images par vidéo | B14: 6 | C14: 6 | D14: 8 | F14: Standard = 6 scènes du calendrier ; Premium ajoute 2 plans.
A15: Prix par image (USD) | B15: 0.021 | C15: 0.045 | D15: 0.045 | F15: Éco : FLUX.2 [dev] 0,012 $/MP × ~1,75 MP. Std/Premium : FLUX.2 [pro] 0,03 $ le 1er MP + 0,015 $/MP suivant, 1024×1792 arrondi à 2 MP (fal.ai).
A16: Voix : prix pour 1 000 caractères (USD) | B16: 0.04 | C16: 0.1 | D16: 0.1 | F16: Éco : Eleven v4 Turbo 0,04 $. Std/Premium : Eleven v3 0,10 $ (fal.ai).
A17: Transcription mot à mot : prix par minute (USD) | B17: 0.008 | C17: 0.008 | D17: 0.008 | F17: ElevenLabs Scribe v2 sur fal.ai : 0,008 $/min.
A18: Clips animés par vidéo | B18: 0 | C18: 1 | D18: 3 | F18: Nombre de plans image-to-video.
A19: Durée d'un clip (s) | B19: 5 | C19: 5 | D19: 5
A20: Prix vidéo par seconde (USD) | B20: 0 | C20: 0.07 | D20: 0.112 | F20: Std : Kling 2.5 Turbo Pro 0,07 $/s. Premium : Kling v3 Pro sans audio 0,112 $/s (fal.ai).
A21: SFX spécifiques générés par vidéo | B21: 0 | C21: 1 | D21: 3 | F21: La banque couvre l'essentiel ; on n'en génère que pour les plans signature.
A22: Prix par SFX (USD, estimation) | B22: 0.02 | C22: 0.02 | D22: 0.02 | F22: Estimation ~0,02 $/effet (tarif ElevenLabs SFX constaté chez d'autres revendeurs) : à vérifier sur fal.
A23: Coût banque audio unique (USD) | B23: 0 | C23: 5.5 | D23: 5.5 | F23: 6 musiques × 1 min à 0,80 $/min (ElevenLabs Music) + 12 SFX. Éco : musiques libres de droits.
A25: Coût par vidéo (USD) | B25: Éco | C25: Standard | D25: Premium
A26: Images | B26: =B14*B15 -> 0.126 | C26: =C14*C15 -> 0.27 | D26: =D14*D15 -> 0.36 | F26: Coûts fixes non comptés : BrightBean (self-host, ton serveur), rendu Remotion en local (gratuit), licence Remotion gratuite pour un indépendant ou une entreprise de 3 personnes max.
A27: Voix off | B27: =$B$6/1000*B16 -> 0.01972 | C27: =$B$6/1000*C16 -> 0.0493 | D27: =$B$6/1000*D16 -> 0.0493
A28: Transcription / sous-titres | B28: =$B$7*B17 -> 0.0043822222 | C28: =$B$7*C17 -> 0.0043822222 | D28: =$B$7*D17 -> 0.0043822222
A29: Clips animés | B29: =B18*B19*B20 -> 0 | C29: =C18*C19*C20 -> 0.35 | D29: =D18*D19*D20 -> 1.68
A30: SFX spécifiques | B30: =B21*B22 -> 0 | C30: =C21*C22 -> 0.02 | D30: =D21*D22 -> 0.06
A31: Banque audio amortie | B31: =B23/($B$8*$B$9) -> 0 | C31: =C23/($B$8*$B$9) -> 0.061111111 | D31: =D23/($B$8*$B$9) -> 0.061111111
A32: Sous-total | B32: =SUM(B26:B31) -> 0.15010222 | C32: =SUM(C26:C31) -> 0.75479333 | D32: =SUM(D26:D31) -> 2.2147933
A33: Marge de régénération | B33: =B32*$B$10 -> 0.045030667 | C33: =C32*$B$10 -> 0.226438 | D33: =D32*$B$10 -> 0.664438
A34: TOTAL PAR VIDÉO (USD) | B34: =B32+B33 -> 0.19513289 | C34: =C32+C33 -> 0.98123133 | D34: =D32+D33 -> 2.8792313
A35: Total par vidéo (EUR) | B35: =B34*$B$11 -> 0.16781428 | C35: =C34*$B$11 -> 0.84385895 | D35: =D34*$B$11 -> 2.4761389
A36: Par jour (EUR) | B36: =B35*$B$8 -> 0.50344285 | C36: =C35*$B$8 -> 2.5315768 | D36: =D35*$B$8 -> 7.4284168
A37: Pour les 90 vidéos (EUR) | B37: =B35*$B$8*$B$9 -> 15.103286 | C37: =C35*$B$8*$B$9 -> 75.947305 | D37: =D35*$B$8*$B$9 -> 222.85251

Sheet Pipeline
A1: Format | B1: Vertical 1080×1920, 30 fps, 30 à 45 s. Hook dans les 2 premières secondes (la 1re phrase du script est écrite pour ça).
A2: Préfixe image (séries A, B, C, D, F) | B2: Cinematic photorealistic space visualization, NASA/ESA documentary style, dramatic volumetric lighting, deep blacks, rich fine detail, vertical 9:16 composition, main subject in the upper two thirds, no text, no letters, no watermark, no logo. Scene:
A3: Préfixe image (série E, histoire) | B3: Cinematic historical recreation, 1950s-1970s space age atmosphere, subtle film grain, warm archival color grading, photorealistic, vertical 9:16 composition, main subject in the upper two thirds, no text, no letters, no watermark, no logo, no real identifiable faces. Scene:
A4: Modèle image | B4: fal-ai/flux-2-pro, image_size 1024×1792. Garder le seed de la scène 1 pour les variantes. Upscale léger dans Remotion (scale 1.06) pour le Ken Burns.
A5: Mouvement | B5: Scène 1 → Kling image-to-video 5 s (Standard : v2.5 Turbo Pro ; Premium : v3 Pro), prompt : « slow cinematic push-in, subtle particle drift, gentle parallax, no camera shake, no morphing ». Autres scènes : Ken Burns + parallaxe 2 couches dans Remotion.
A6: Voix | B6: fal-ai/elevenlabs/tts/eleven-v3, langue fr, une seule voix narrateur pour toute la chaîne (identité sonore). Stabilité ~0,5, style ~0,3. Tester 3 voix sur le script A01 avant de figer. Balises possibles : [whispers], [excited] avec parcimonie.
A7: Sous-titres (qualité) | B7: Timestamps mot à mot via Scribe v2, réalignés sur le texte exact du script (pas de faute de transcription). 2 à 4 mots par groupe, 1 ligne, 2 max. Police Montserrat ExtraBold ~78 px, blanc, contour noir 6 px + ombre douce. Mot prononcé en surbrillance (jaune #FFD84D) avec pop scale 1.08. Position : ~62 % de la hauteur (hors zone UI TikTok/Reels en bas et à droite). Chiffres clés en couleur accent.
A8: Audio | B8: Voix à -14 LUFS intégrés. Musique de la banque à ~-18 dB sous la voix avec ducking. SFX calés sur les changements de scène et les chiffres chocs. Fade out 1 s.
A9: Montage Remotion | B9: Composition « SpaceShort » : props = {id, script, words[], scenes[], clip, sfx[], music}. Chaque scène démarre sur le début d'une phrase (répartition proportionnelle au texte). Transitions : fondu 8 frames ou whoosh + zoom. Barre de progression fine en haut. Carton final 1,5 s avec la question de la légende.
A10: Couverture | B10: Frame de la scène 1 + titre court en gros (3-5 mots) généré dans Remotion (pas dans l'image IA).
A11: Publication | B11: BrightBean : TikTok, Reels, YouTube Shorts. Créneaux 08:00 / 12:30 / 19:00. Activer le label contenu généré par IA sur chaque plateforme. Légende = colonne S.
A12: Contrôle qualité | B12: Avant publication : relire le script, vérifier les sous-titres mot à mot, écarter toute image avec texte parasite, visage réel reconnaissable ou logo, écouter la vidéo en entier.
A14: PROMPT MAÎTRE | B14: Tu es mon producteur vidéo pour la chaîne Espace. Tu disposes des connecteurs BrightBean (publication), Remotion (rendu) et d'une clé fal.ai. Pour chaque ligne du Calendrier au statut « À produire » : 1) génère la voix avec le script exact, 2) récupère les timestamps mot à mot et réaligne-les sur le script, 3) génère les 6 images avec leurs prompts, 4) anime la scène 1, 5) récupère SFX et musique dans la banque, 6) monte avec la composition SpaceShort selon l'onglet Pipeline, 7) montre-moi la vidéo et un résumé des coûts avant de programmer, 8) après mon feu vert, programme-la sur BrightBean au créneau indiqué avec la légende. Travaille par lot de 3 vidéos (une journée). Si une image contient du texte, un logo ou un visage réel reconnaissable, régénère-la avec un autre seed. Ne publie jamais sans validation.

Sheet Banque audio
A1: Type | B1: Clé | C1: Prompt de génération (fal.ai) | D1: Utilisations
A2: SFX | B2: whoosh | C2: Deep cinematic whoosh transition, airy, 1.5 seconds | D2: =COUNTIF(Calendrier!Q2:Q91,"*whoosh*") -> 44
A3: SFX | B3: deep_boom | C3: Low cinematic sub boom impact with long reverb tail, 3 seconds | D3: =COUNTIF(Calendrier!Q2:Q91,"*deep_boom*") -> 27
A4: SFX | B4: riser | C4: Tension riser building up, synth and strings, 4 seconds | D4: =COUNTIF(Calendrier!Q2:Q91,"*riser*") -> 19
A5: SFX | B5: rumble | C5: Deep seismic rumble, low frequency, 4 seconds | D5: =COUNTIF(Calendrier!Q2:Q91,"*rumble*") -> 16
A6: SFX | B6: beep | C6: Vintage spacecraft radio beep sequence, clean, 2 seconds | D6: =COUNTIF(Calendrier!Q2:Q91,"*beep*") -> 13
A7: SFX | B7: heartbeat | C7: Slow tense heartbeat, muffled, 4 seconds | D7: =COUNTIF(Calendrier!Q2:Q91,"*heartbeat*") -> 5
A8: SFX | B8: wind | C8: Thin alien wind over a desert, ambient, 5 seconds | D8: =COUNTIF(Calendrier!Q2:Q91,"*wind*") -> 11
A9: SFX | B9: crackle | C9: Hot crackling lava and sizzling rocks, 3 seconds | D9: =COUNTIF(Calendrier!Q2:Q91,"*crackle*") -> 5
A10: SFX | B10: glass_crack | C10: Ice or rock cracking under stress, sharp, 2 seconds | D10: =COUNTIF(Calendrier!Q2:Q91,"*glass_crack*") -> 3
A11: SFX | B11: launch | C11: Rocket engine ignition and roaring liftoff, distant, 5 seconds | D11: =COUNTIF(Calendrier!Q2:Q91,"*launch*") -> 8
A12: SFX | B12: static | C12: Radio static burst with interference, 2 seconds | D12: =COUNTIF(Calendrier!Q2:Q91,"*static*") -> 5
A13: SFX | B13: chime | C13: Soft magical shimmer chime, sparkling, 2 seconds | D13: =COUNTIF(Calendrier!Q2:Q91,"*chime*") -> 31
A14: Musique | B14: epic | C14: Epic cinematic space ambient, slow build, deep drums, choir pads, no vocals, loopable | D14: =COUNTIF(Calendrier!R2:R91,"epic") -> 19
A15: Musique | B15: mystery | C15: Mysterious dark space ambient, low drones, sparse piano, no vocals, loopable | D15: =COUNTIF(Calendrier!R2:R91,"mystery") -> 12
A16: Musique | B16: wonder | C16: Wonder and awe space ambient, soft arpeggios, warm synth pads, no vocals, loopable | D16: =COUNTIF(Calendrier!R2:R91,"wonder") -> 22
A17: Musique | B17: tension | C17: Tense suspenseful sci-fi underscore, pulsing bass, ticking, no vocals, loopable | D17: =COUNTIF(Calendrier!R2:R91,"tension") -> 12
A18: Musique | B18: retro | C18: 1960s space race documentary underscore, retro analog synth and light orchestra, no vocals, loopable | D18: =COUNTIF(Calendrier!R2:R91,"retro") -> 7
A19: Musique | B19: calm | C19: Calm contemplative space ambient, gentle pads, slow evolving, no vocals, loopable | D19: =COUNTIF(Calendrier!R2:R91,"calm") -> 18
A21: SFX : ElevenLabs Sound Effects via fal. Musiques : ElevenLabs Music via fal (0,80 $/min), 1 min chacune, bouclables. Générer 2 variantes par clé et garder la meilleure.
